apigw_iam_client.py
setup.py
apigw_iam_client.egg-info/PKG-INFO
apigw_iam_client.egg-info/SOURCES.txt
apigw_iam_client.egg-info/dependency_links.txt
apigw_iam_client.egg-info/requires.txt
apigw_iam_client.egg-info/top_level.txt