Metadata-Version: 2.1
Name: apigw-iam-client
Version: 0.1
Summary: AWS API Gateway Client Lib for IAM Authorized APIs
Home-page: https://github.com/kapilt/apigw-iam-client
Author: Kapil Thangavelu
Author-email: kapil.foss@gmail.com
License: Apache-2.0
Platform: UNKNOWN
